setup.py
gitcepter/__init__.py
gitcepter/changes.py
gitcepter/checks.py
gitcepter/consts.py
gitcepter/env.py
gitcepter/file.py
gitcepter/install.py
gitcepter/log.py
gitcepter/utils.py
gitcepter.egg-info/PKG-INFO
gitcepter.egg-info/SOURCES.txt
gitcepter.egg-info/dependency_links.txt
gitcepter.egg-info/entry_points.txt
gitcepter.egg-info/top_level.txt
gitcepter/client/__init__.py
gitcepter/client/gitcepter.py
gitcepter/server/__init__.py
gitcepter/server/commit.py
gitcepter/server/gitcepter.py