Metadata-Version: 1.0
Name: gitcepter
Version: 0.1.8
Summary: Git interceptor to check commits and code style
Home-page: http://appinstall.aiyoumi.com:8282/qinchao/gitcepter.git
Author: chao
Author-email: qch5240@163.com
License: MIT
Keywords: syntax-checker git git-hook python
Platform: POSIX
